divinate/__init__.py
divinate/core/__init__.py
divinate/core/base.py
divinate/core/discounting.py
divinate/core/flows.py
divinate/core/model.py
divinate/core/precision.py
divinate-0.1.2.dist-info/LICENSE
divinate-0.1.2.dist-info/METADATA
divinate-0.1.2.dist-info/WHEEL
divinate-0.1.2.dist-info/top_level.txt
divinate-0.1.2.dist-info/RECORD
