Metadata-Version: 2.1
Name: divinate
Version: 0.1.2
Summary: A framework for Actuarial modelling.
Home-page: https://github.com/RatulMaharaj/divinate
Author: Ratul Maharaj
Author-email: ratulmaharaj@gmail.com
Project-URL: Bug Tracker, https://github.com/RatulMaharaj/divinate/issues
Classifier: Programming Language :: Python :: 3
Classifier: License :: OSI Approved :: MIT License
Classifier: Operating System :: OS Independent
Requires-Python: >=3.8
License-File: LICENSE
Requires-Dist: pandas
Requires-Dist: numpy
